{
  "id": "a2ef7f0e-7139-4ab7-basicdiet-local",
  "name": "BasicDiet Local",
  "values": [
    {
      "key": "baseUrl",
      "value": "https://basicdiet145.onrender.com",
      "type": "default",
      "enabled": true
    },
    {
      "key": "dashboardToken",
      "value": "",
      "type": "default",
      "enabled": true
    },
    {
      "key": "adminToken",
      "value": "",
      "type": "default",
      "enabled": true
    },
    {
      "key": "courierToken",
      "value": "",
      "type": "default",
      "enabled": true
    },
    {
      "key": "kitchenToken",
      "value": "",
      "type": "default",
      "enabled": true
    },
    {
      "key": "clientToken",
      "value": "",
      "type": "default",
      "enabled": true
    },
    {
      "key": "testDate",
      "value": "2026-06-13",
      "type": "default",
      "enabled": true
    },
    {
      "key": "dateDay1",
      "value": "2026-06-13",
      "type": "default",
      "enabled": true
    },
    {
      "key": "dateDay2",
      "value": "2026-06-14",
      "type": "default",
      "enabled": true
    },
    {
      "key": "deliverySubscriptionId",
      "value": "6a2ce700c2ce6c0528b5c9b2",
      "type": "default",
      "enabled": true
    },
    {
      "key": "deliverySubscriptionDayId",
      "value": "6a2ce701c2ce6c0528b5c9cd",
      "type": "default",
      "enabled": true
    },
    {
      "key": "pickupSubscriptionId",
      "value": "6a2c99810b2e4dde85b23a72",
      "type": "default",
      "enabled": true
    },
    {
      "key": "pickupSubscriptionDayId",
      "value": "6a2c99810b2e4dde85b23a76",
      "type": "default",
      "enabled": true
    },
    {
      "key": "entityId",
      "value": "6a2ce701c2ce6c0528b5c9cd",
      "type": "default",
      "enabled": true
    },
    {
      "key": "entityType",
      "value": "subscription_day",
      "type": "default",
      "enabled": true
    },
    {
      "key": "pickupRequestId",
      "value": "",
      "type": "default",
      "enabled": true
    },
    {
      "key": "deliveryId",
      "value": "6a2ce70143990b927254bda7",
      "type": "default",
      "enabled": true
    },
    {
      "key": "manualDeductionSubscriptionId",
      "value": "6a2c99810b2e4dde85b23a72",
      "type": "default",
      "enabled": true
    },
    {
      "key": "orderId",
      "value": "6a272c39eb023cfd3cff5a32",
      "type": "default",
      "enabled": true
    },
    {
      "key": "lastResponseStatus",
      "value": "",
      "type": "default",
      "enabled": true
    },
    {
      "key": "lastErrorCode",
      "value": "",
      "type": "default",
      "enabled": true
    },
    {
      "key": "customerPhone",
      "value": "+966500000001",
      "type": "default",
      "enabled": true
    },
    {
      "key": "dashboardEmail",
      "value": "",
      "type": "default",
      "enabled": true
    },
    {
      "key": "dashboardPassword",
      "value": "",
      "type": "default",
      "enabled": true
    }
  ],
  "_postman_variable_scope": "environment",
  "_postman_exported_at": "2026-06-13T05:13:39.185Z",
  "_postman_exported_using": "Codex"
}
